Metadata-Version: 1.0
Name: PyPR
Version: 0.1.1
Summary: Python Pattern Recognition
Home-page: http://www.decision3.com/jpp
Author: Joan Petur Petersen
Author-email: joanpeturpetersen@gmail.com
License: UNKNOWN
Platform: UNKNOWN
